app_conf/__init__.py
app_conf/casting.py
app_conf/common.py
app_conf/func_sigs.py
app_conf/help.py
app_conf/version.py
app_conf-20181011.dist-info/LICENSE.txt
app_conf-20181011.dist-info/METADATA
app_conf-20181011.dist-info/RECORD
app_conf-20181011.dist-info/WHEEL
app_conf-20181011.dist-info/entry_points.txt
app_conf-20181011.dist-info/top_level.txt
