Metadata-Version: 2.1
Name: app-conf
Version: 20181011
Summary: Application Config
Home-page: http://github.com/axiros/app_conf
Author: Axiros GmbH
Author-email: gk@axiros.com
License: UNKNOWN
Download-URL: http://github.com/axiros/app_conf/tarball/
Keywords: app,config,source code
Platform: UNKNOWN
Classifier: Programming Language :: Python
Classifier: Natural Language :: English
Classifier: Operating System :: POSIX
Classifier: Topic :: Software Development :: Pre-processors
Classifier: Topic :: Software Development :: Libraries :: Python Modules
Classifier: Topic :: Software Development :: Code Generators
Classifier: Development Status :: 3 - Alpha
Classifier: License :: OSI Approved :: BSD License
Classifier: Programming Language :: Python :: 2.7
Classifier: Programming Language :: Python :: 3.6
Classifier: Programming Language :: Python :: 3.7
Provides-Extra: tests
